cdktf_cdktf_provider_datadog/__init__.py
cdktf_cdktf_provider_datadog/py.typed
cdktf_cdktf_provider_datadog/_jsii/__init__.py
cdktf_cdktf_provider_datadog/_jsii/provider-datadog@12.14.0.jsii.tgz
cdktf_cdktf_provider_datadog/action_connection/__init__.py
cdktf_cdktf_provider_datadog/agentless_scanning_aws_scan_options/__init__.py
cdktf_cdktf_provider_datadog/agentless_scanning_gcp_scan_options/__init__.py
cdktf_cdktf_provider_datadog/api_key/__init__.py
cdktf_cdktf_provider_datadog/apm_retention_filter/__init__.py
cdktf_cdktf_provider_datadog/apm_retention_filter_order/__init__.py
cdktf_cdktf_provider_datadog/app_builder_app/__init__.py
cdktf_cdktf_provider_datadog/app_key_registration/__init__.py
cdktf_cdktf_provider_datadog/application_key/__init__.py
cdktf_cdktf_provider_datadog/appsec_waf_custom_rule/__init__.py
cdktf_cdktf_provider_datadog/appsec_waf_exclusion_filter/__init__.py
cdktf_cdktf_provider_datadog/authn_mapping/__init__.py
cdktf_cdktf_provider_datadog/aws_cur_config/__init__.py
cdktf_cdktf_provider_datadog/azure_uc_config/__init__.py
cdktf_cdktf_provider_datadog/child_organization/__init__.py
cdktf_cdktf_provider_datadog/cloud_configuration_rule/__init__.py
cdktf_cdktf_provider_datadog/cloud_workload_security_agent_rule/__init__.py
cdktf_cdktf_provider_datadog/compliance_custom_framework/__init__.py
cdktf_cdktf_provider_datadog/compliance_resource_evaluation_filter/__init__.py
cdktf_cdktf_provider_datadog/cost_budget/__init__.py
cdktf_cdktf_provider_datadog/csm_threats_agent_rule/__init__.py
cdktf_cdktf_provider_datadog/csm_threats_policy/__init__.py
cdktf_cdktf_provider_datadog/custom_allocation_rule/__init__.py
cdktf_cdktf_provider_datadog/custom_allocation_rules/__init__.py
cdktf_cdktf_provider_datadog/dashboard/__init__.py
cdktf_cdktf_provider_datadog/dashboard_json/__init__.py
cdktf_cdktf_provider_datadog/dashboard_list/__init__.py
cdktf_cdktf_provider_datadog/data_datadog_action_connection/__init__.py
cdktf_cdktf_provider_datadog-12.14.0.dist-info/LICENSE
cdktf_cdktf_provider_datadog-12.14.0.dist-info/METADATA
cdktf_cdktf_provider_datadog-12.14.0.dist-info/WHEEL
cdktf_cdktf_provider_datadog-12.14.0.dist-info/top_level.txt
cdktf_cdktf_provider_datadog-12.14.0.dist-info/RECORD
